verbose_octo_goggles/__init__.py
verbose_octo_goggles/config.py
verbose_octo_goggles/core.py
verbose_octo_goggles/utils.py
verbose_octo_goggles/adapter/__init__.py
verbose_octo_goggles/adapter/base.py
verbose_octo_goggles/adapter/console.py
verbose_octo_goggles/adapter/django_model.py
verbose_octo_goggles/adapter/empty.py
verbose_octo_goggles/management/__init__.py
verbose_octo_goggles/management/commands/__init__.py
verbose_octo_goggles/management/commands/run_import.py
verbose_octo_goggles/reader/__init__.py
verbose_octo_goggles/reader/base.py
verbose_octo_goggles/reader/http.py
verbose_octo_goggles/reader/rss.py
verbose_octo_goggles-0.1.dist-info/DESCRIPTION.rst
verbose_octo_goggles-0.1.dist-info/METADATA
verbose_octo_goggles-0.1.dist-info/RECORD
verbose_octo_goggles-0.1.dist-info/WHEEL
verbose_octo_goggles-0.1.dist-info/metadata.json
verbose_octo_goggles-0.1.dist-info/top_level.txt
