Metadata-Version: 2.0
Name: verbose-octo-goggles
Version: 0.1
Summary: A sample Python project
Home-page: https://github.com/i2xS/verbose-octo-goggles.git
Author: 2xS
Author-email: pypa-dev@googlegroups.com
License: MIT
Keywords: Super duper thing does nothing
Platform: UNKNOWN
Classifier: Development Status :: 3 - Alpha
Classifier: Intended Audience :: Developers
Classifier: Topic :: Software Development :: Build Tools
Classifier: License :: OSI Approved :: MIT License
Classifier: Programming Language :: Python :: 2
Classifier: Programming Language :: Python :: 2.7
Provides-Extra: dev
Requires-Dist: check-manifest; extra == 'dev'
Provides-Extra: test
Requires-Dist: coverage; extra == 'test'
